{
  "updated_at": "2026-07-20T20:17:34.930Z",
  "project_id": "SOLAN-BUS",
  "query": "\"Solan Old Bus Stand Redevelopment\" Himachal",
  "counts": {
    "videos": 3,
    "comments": 39
  },
  "videos": [
    {
      "videoId": "9tO7ISbEDc4",
      "title": "kuch aisa hai Himachal Pradesh ka industrial area Baddi ♥️|| #trending #trendingshorts #tranding",
      "channel": "Aryan Vlogs",
      "published_at": "2023-03-20T09:07:02Z",
      "description": "",
      "comment_count": 19,
      "comments": [
        {
          "comment_id": "UgwsbroLsdlYwkammNV4AaABAg",
          "author": "@Mahesharyan2021",
          "text": "Thanks ❤",
          "like_count": 2,
          "published_at": "2026-06-15T04:02:04Z"
        },
        {
          "comment_id": "UgwlCsL4cceCl1CNU7R4AaABAg",
          "author": "@yugkalwani",
          "text": "Shiva biogentic pharmaceuticals kaisa h",
          "like_count": 1,
          "published_at": "2026-05-26T09:39:46Z"
        },
        {
          "comment_id": "UgwUDtEBCUHwONAtG0F4AaABAg",
          "author": "@NeerajTiwari-v4m",
          "text": "Bhai job mil jayega",
          "like_count": 1,
          "published_at": "2026-03-24T14:53:25Z"
        },
        {
          "comment_id": "Ugz5n_rmMeuMUElsm594AaABAg",
          "author": "@riyarana5733",
          "text": "Pharma company me job mil skti hai kya",
          "like_count": 0,
          "published_at": "2025-09-22T08:38:01Z"
        },
        {
          "comment_id": "UgwrtHvsoeoafYWAnPt4AaABAg",
          "author": "@MYEditz69",
          "text": "Bihar",
          "like_count": 2,
          "published_at": "2025-10-26T04:04:40Z"
        },
        {
          "comment_id": "UgzdZjO2sNWWD18SGql4AaABAg",
          "author": "@miguel45x",
          "text": "Bhai koi job milega kya please help me",
          "like_count": 0,
          "published_at": "2025-01-22T04:20:49Z"
        },
        {
          "comment_id": "Ugwd5fuBpOxloEFAxWB4AaABAg",
          "author": "@GovindSingh-cd1ju",
          "text": "Hello",
          "like_count": 2,
          "published_at": "2025-06-28T12:21:54Z"
        },
        {
          "comment_id": "UgyGtx5nR9zDGwIRddF4AaABAg",
          "author": "@somnathkarmakar58",
          "text": "Job hum",
          "like_count": 0,
          "published_at": "2026-07-08T16:33:30Z"
        },
        {
          "comment_id": "UgyXpzBX0-7CKc2mvZt4AaABAg",
          "author": "@SanuKumar-t2m",
          "text": "भाई यहीं पर तो मैं काम करता है हिमाचल प्रदेश बद्दी यूनिकेम चौक यूनिकेम  limited company",
          "like_count": 2,
          "published_at": "2026-02-17T12:30:48Z"
        },
        {
          "comment_id": "UgwRZe4TMAq__JqAsjJ4AaABAg",
          "author": "@ruhirajput1122",
          "text": "Nhi milti yha job m do month se preshan ho gyi dhund dhund kr",
          "like_count": 3,
          "published_at": "2025-09-03T13:13:32Z"
        },
        {
          "comment_id": "Ugz-tyFYJ6m2piictJN4AaABAg",
          "author": "@RajakumarRaja-di2np",
          "text": "Koi job milega kya help me bro",
          "like_count": 1,
          "published_at": "2024-09-01T05:01:51Z"
        },
        {
          "comment_id": "UgzSg8uidB_7GMBg0xl4AaABAg",
          "author": "@sitaramhnuman706",
          "text": "❤😅😮😂",
          "like_count": 1,
          "published_at": "2023-04-19T16:16:57Z"
        },
        {
          "comment_id": "UgxpnTUS05AeCb6Eju54AaABAg",
          "author": "@PritamKumar-xw2ey",
          "text": "Koi kam milega yaha bhai",
          "like_count": 1,
          "published_at": "2025-06-06T12:19:28Z"
        },
        {
          "comment_id": "UgydX1Ju_DGKN8kbqPF4AaABAg",
          "author": "@GovindSingh-cd1ju",
          "text": "Mobai no",
          "like_count": 1,
          "published_at": "2025-06-28T12:22:10Z"
        },
        {
          "comment_id": "UgzrJUSAyTIc8outaDx4AaABAg",
          "author": "@devansh1276",
          "text": "As a Kangri yeh Himachal hai ? 😂",
          "like_count": 0,
          "published_at": "2025-11-11T20:16:28Z"
        },
        {
          "comment_id": "UgwE6WfPuRaGOUOijsV4AaABAg",
          "author": "@deeply_joyed",
          "text": "Bohot hi bekar jagah hai",
          "like_count": 2,
          "published_at": "2025-10-02T14:02:25Z"
        },
        {
          "comment_id": "UgzyKVehNN8joWYv7XN4AaABAg",
          "author": "@ravinderkrishan5351",
          "text": "Congress ho yA BJP Baddi ka naam dono nai kharab kiya",
          "like_count": 0,
          "published_at": "2026-01-07T12:18:39Z"
        },
        {
          "comment_id": "UgwgSv_Um5U5nSf3BrV4AaABAg",
          "author": "@RajKumar-j5q6j",
          "text": "Hi",
          "like_count": 0,
          "published_at": "2026-02-15T05:22:47Z"
        },
        {
          "comment_id": "Ugx9W-K5GZkIla26RMZ4AaABAg",
          "author": "@AnilKumar-oi7gi",
          "text": "Hi",
          "like_count": 1,
          "published_at": "2026-02-17T14:50:06Z"
        }
      ]
    },
    {
      "videoId": "cFLW9oE558U",
      "title": "7 लाख में नया मकान| independant house in delhi ncr| cheapest plot in delhi ncr",
      "channel": "Musafir Sandeep",
      "published_at": "2025-05-26T02:42:36Z",
      "description": "plots #realestate #cheapestpropertyindelhincr #home #3bhkflatindelhincr #property #jadsemakaanomvihar #flats ...",
      "comment_count": 20,
      "comments": [
        {
          "comment_id": "UgxEd4MSgG1LoTpL5uZ4AaABAg",
          "author": "@Gyan-lb3sw",
          "text": "कितने गज में है और कहां पर है",
          "like_count": 16,
          "published_at": "2025-09-21T06:08:50Z"
        },
        {
          "comment_id": "UgypwWP3Y8bDyeUAZ9h4AaABAg",
          "author": "@RamRaman-x9n",
          "text": "Kaha hai aur kahi gir to nhi jayega kaise utha liya material kaisa lagaya hai",
          "like_count": 1,
          "published_at": "2026-05-31T09:48:02Z"
        },
        {
          "comment_id": "UgypgkJKQ8k-VlRJ-z54AaABAg",
          "author": "@RahulTiwari-b4i",
          "text": "Bhaiya kis jagah per hai Raebareli mein aur kist kitne kategi cast kitne Ko Hoga",
          "like_count": 0,
          "published_at": "2026-06-10T16:04:18Z"
        },
        {
          "comment_id": "UgytlgdTG2pgKoPArot4AaABAg",
          "author": "@rajaramgurjar9810",
          "text": "Yah kaha per hai sir our kitna varg gaj hai",
          "like_count": 0,
          "published_at": "2025-10-10T03:40:08Z"
        },
        {
          "comment_id": "UgyVFwbMo3vFPKU1jKx4AaABAg",
          "author": "@Karankumar-w5b2l",
          "text": "Bhai registry bhi Pakki hai ya FIR aisi chij ki FIR Bhag jana hai yah Do Number Ka Makan hai",
          "like_count": 0,
          "published_at": "2026-01-08T01:56:38Z"
        },
        {
          "comment_id": "UgzlLjIY6ZRM_qwXIX54AaABAg",
          "author": "@Goldgehu",
          "text": "Kya abhi available h im interested",
          "like_count": 0,
          "published_at": "2025-08-02T10:19:15Z"
        },
        {
          "comment_id": "UgwZ5s7d7yYZ1WnLf1l4AaABAg",
          "author": "@ramavtar151",
          "text": "Location total price",
          "like_count": 0,
          "published_at": "2025-07-21T19:31:29Z"
        },
        {
          "comment_id": "UgwHNHm9aB6ccpia5N54AaABAg",
          "author": "@freeTitan6053",
          "text": "Kaha landa baazar Lahore ki property hai?",
          "like_count": 0,
          "published_at": "2025-11-04T13:31:02Z"
        },
        {
          "comment_id": "UgxWtU6pwZ_F-r-SWvZ4AaABAg",
          "author": "@RakeshKumarsainik",
          "text": "Are bhai video banate ho to location bhi bata diya karo",
          "like_count": 7,
          "published_at": "2025-08-11T06:06:47Z"
        },
        {
          "comment_id": "Ugw7DLDf6mLhQVcMyPZ4AaABAg",
          "author": "@Govind.uk01",
          "text": "Location kaha ki hai",
          "like_count": 0,
          "published_at": "2025-08-21T14:04:16Z"
        },
        {
          "comment_id": "UgyQiS5HpF6xW4VlrSh4AaABAg",
          "author": "@anshuldesaiwal5309",
          "text": "Khaa pr hi y bhi",
          "like_count": 0,
          "published_at": "2025-08-06T14:28:56Z"
        },
        {
          "comment_id": "UgyvSuJYuskvCLeKeNZ4AaABAg",
          "author": "@rajrajSingh-v9u",
          "text": "Inke chakkar me na pade koi bhi sab frad hai",
          "like_count": 8,
          "published_at": "2025-11-23T07:00:24Z"
        },
        {
          "comment_id": "UgxfZAI2ZMG5PBtThVB4AaABAg",
          "author": "@NehaKumari-hg3rl",
          "text": "Kahan per hai",
          "like_count": 0,
          "published_at": "2025-08-25T03:51:16Z"
        },
        {
          "comment_id": "UgwGhSgpE79PpcmyWwN4AaABAg",
          "author": "@sulemabano7636",
          "text": "Aapko contact kaise karen",
          "like_count": 2,
          "published_at": "2025-09-06T16:46:23Z"
        },
        {
          "comment_id": "UgyhCgwRQWSp7jZ6F1N4AaABAg",
          "author": "@priyamaheshwari9989",
          "text": "Pura price bataye",
          "like_count": 0,
          "published_at": "2025-09-04T04:07:36Z"
        },
        {
          "comment_id": "Ugw-r7Cp-BH1DQebv3p4AaABAg",
          "author": "@zeeshansiddiqui1284",
          "text": "Kis jagha par hai bhai",
          "like_count": 2,
          "published_at": "2025-09-04T17:35:04Z"
        },
        {
          "comment_id": "UgxTGK9xJTyGr81Bb7B4AaABAg",
          "author": "@akashkumar-hx2tq",
          "text": "Kha pe hai ye",
          "like_count": 0,
          "published_at": "2025-10-26T17:12:15Z"
        },
        {
          "comment_id": "UgxE2uSl3Gr3me85tVN4AaABAg",
          "author": "@AasiyaKhatoon-k9o",
          "text": "Kaha pr",
          "like_count": 0,
          "published_at": "2025-10-29T02:35:03Z"
        },
        {
          "comment_id": "UgxGssdHfXucYXlADFV4AaABAg",
          "author": "@padamgupta7027",
          "text": "कहां पर है कृपया बताएं",
          "like_count": 2,
          "published_at": "2025-11-24T09:50:59Z"
        },
        {
          "comment_id": "Ugxkocg5qmGNGxA-vyp4AaABAg",
          "author": "@vandanakanojia88",
          "text": "Location please",
          "like_count": 0,
          "published_at": "2025-10-14T14:09:15Z"
        }
      ]
    },
    {
      "videoId": "KikzUYzTn_4",
      "title": "A short drive on Shili - Jaunaji Road in Solan",
      "channel": "Unpopular Explorer",
      "published_at": "2020-08-31T17:15:42Z",
      "description": "",
      "comment_count": 0,
      "comments": []
    }
  ],
  "methodology": "YouTube Data API v3 search for the project name (India region). Top 3 videos by relevance; top 20 comments per video."
}
